[{"word": "a", "number": 7, "filenames": ["files/a0.mp3", "files/a1.mp3", "files/a2.mp3", "files/a3.mp3", "files/a4.mp3", "files/a5.mp3", "files/a6.mp3"]}, {"word": "acqu\u00e9reur", "number": 1, "filenames": ["files/acqu\u00e9reur0.mp3"]}, {"word": "acqu\u00e9rir", "number": 2, "filenames": ["files/acqu\u00e9rir0.mp3", "files/acqu\u00e9rir1.mp3"]}, {"word": "afin", "number": 1, "filenames": ["files/afin0.mp3"]}, {"word": "agent", "number": 3, "filenames": ["files/agent0.mp3", "files/agent1.mp3", "files/agent2.mp3"]}, {"word": "agit", "number": 2, "filenames": ["files/agit0.mp3", "files/agit1.mp3"]}, {"word": "aide", "number": 2, "filenames": ["files/aide0.mp3", "files/aide1.mp3"]}, {"word": "ainsi", "number": 5, "filenames": ["files/ainsi0.mp3", "files/ainsi1.mp3", "files/ainsi2.mp3", "files/ainsi3.mp3", "files/ainsi4.mp3"]}, {"word": "ais\u00e9", "number": 1, "filenames": ["files/ais\u00e90.mp3"]}, {"word": "ait", "number": 1, "filenames": ["files/ait0.mp3"]}, {"word": "allait", "number": 1, "filenames": ["files/allait0.mp3"]}, {"word": "allant", "number": 1, "filenames": ["files/allant0.mp3"]}, {"word": "aller", "number": 3, "filenames": ["files/aller0.mp3", "files/aller1.mp3", "files/aller2.mp3"]}, {"word": "allons", "number": 1, "filenames": ["files/allons0.mp3"]}, {"word": "allure", "number": 1, "filenames": ["files/allure0.mp3"]}, {"word": "alors", "number": 4, "filenames": ["files/alors0.mp3", "files/alors1.mp3", "files/alors2.mp3", "files/alors3.mp3"]}, {"word": "ambitieux", "number": 2, "filenames": ["files/ambitieux0.mp3", "files/ambitieux1.mp3"]}, {"word": "ambition", "number": 1, "filenames": ["files/ambition0.mp3"]}, {"word": "ami", "number": 6, "filenames": ["files/ami0.mp3", "files/ami1.mp3", "files/ami2.mp3", "files/ami3.mp3", "files/ami4.mp3", "files/ami5.mp3"]}, {"word": "art", "number": 3, "filenames": ["files/art0.mp3", "files/art1.mp3", "files/art2.mp3"]}, {"word": "assis", "number": 2, "filenames": ["files/assis0.mp3", "files/assis1.mp3"]}, {"word": "aura", "number": 1, "filenames": ["files/aura0.mp3"]}, {"word": "aussi", "number": 4, "filenames": ["files/aussi0.mp3", "files/aussi1.mp3", "files/aussi2.mp3", "files/aussi3.mp3"]}, {"word": "auteur", "number": 1, "filenames": ["files/auteur0.mp3"]}, {"word": "autour", "number": 2, "filenames": ["files/autour0.mp3", "files/autour1.mp3"]}, {"word": "autre", "number": 3, "filenames": ["files/autre0.mp3", "files/autre1.mp3", "files/autre2.mp3"]}, {"word": "avait", "number": 1, "filenames": ["files/avait0.mp3"]}, {"word": "avant", "number": 6, "filenames": ["files/avant0.mp3", "files/avant1.mp3", "files/avant2.mp3", "files/avant3.mp3", "files/avant4.mp3", "files/avant5.mp3"]}, {"word": "avez", "number": 1, "filenames": ["files/avez0.mp3"]}, {"word": "avis", "number": 1, "filenames": ["files/avis0.mp3"]}, {"word": "avons", "number": 1, "filenames": ["files/avons0.mp3"]}, {"word": "avoue", "number": 1, "filenames": ["files/avoue0.mp3"]}, {"word": "axa", "number": 1, "filenames": ["files/axa0.mp3"]}, {"word": "axe", "number": 1, "filenames": ["files/axe0.mp3"]}, {"word": "ax\u00e9", "number": 1, "filenames": ["files/ax\u00e90.mp3"]}, {"word": "b", "number": 4, "filenames": ["files/b0.mp3", "files/b1.mp3", "files/b2.mp3", "files/b3.mp3"]}, {"word": "bain", "number": 4, "filenames": ["files/bain0.mp3", "files/bain1.mp3", "files/bain2.mp3", "files/bain3.mp3"]}, {"word": "balle", "number": 3, "filenames": ["files/balle0.mp3", "files/balle1.mp3", "files/balle2.mp3"]}, {"word": "bar", "number": 1, "filenames": ["files/bar0.mp3"]}, {"word": "bas", "number": 3, "filenames": ["files/bas0.mp3", "files/bas1.mp3", "files/bas2.mp3"]}, {"word": "basse", "number": 3, "filenames": ["files/basse0.mp3", "files/basse1.mp3", "files/basse2.mp3"]}, {"word": "beau", "number": 4, "filenames": ["files/beau0.mp3", "files/beau1.mp3", "files/beau2.mp3", "files/beau3.mp3"]}, {"word": "belle", "number": 4, "filenames": ["files/belle0.mp3", "files/belle1.mp3", "files/belle2.mp3", "files/belle3.mp3"]}, {"word": "ben", "number": 1, "filenames": ["files/ben0.mp3"]}, {"word": "beurre", "number": 6, "filenames": ["files/beurre0.mp3", "files/beurre1.mp3", "files/beurre2.mp3", "files/beurre3.mp3", "files/beurre4.mp3", "files/beurre5.mp3"]}, {"word": "biais", "number": 1, "filenames": ["files/biais0.mp3"]}, {"word": "bien", "number": 6, "filenames": ["files/bien0.mp3", "files/bien1.mp3", "files/bien2.mp3", "files/bien3.mp3", "files/bien4.mp3", "files/bien5.mp3"]}, {"word": "bit", "number": 1, "filenames": ["files/bit0.mp3"]}, {"word": "blanc", "number": 5, "filenames": ["files/blanc0.mp3", "files/blanc1.mp3", "files/blanc2.mp3", "files/blanc3.mp3", "files/blanc4.mp3"]}, {"word": "bleu", "number": 6, "filenames": ["files/bleu0.mp3", "files/bleu1.mp3", "files/bleu2.mp3", "files/bleu3.mp3", "files/bleu4.mp3", "files/bleu5.mp3"]}, {"word": "bob", "number": 1, "filenames": ["files/bob0.mp3"]}, {"word": "bombe", "number": 2, "filenames": ["files/bombe0.mp3", "files/bombe1.mp3"]}, {"word": "bon", "number": 4, "filenames": ["files/bon0.mp3", "files/bon1.mp3", "files/bon2.mp3", "files/bon3.mp3"]}, {"word": "bonne", "number": 5, "filenames": ["files/bonne0.mp3", "files/bonne1.mp3", "files/bonne2.mp3", "files/bonne3.mp3", "files/bonne4.mp3"]}, {"word": "bord", "number": 3, "filenames": ["files/bord0.mp3", "files/bord1.mp3", "files/bord2.mp3"]}, {"word": "boule", "number": 1, "filenames": ["files/boule0.mp3"]}, {"word": "bout", "number": 3, "filenames": ["files/bout0.mp3", "files/bout1.mp3", "files/bout2.mp3"]}, {"word": "bouton", "number": 3, "filenames": ["files/bouton0.mp3", "files/bouton1.mp3", "files/bouton2.mp3"]}, {"word": "bras", "number": 4, "filenames": ["files/bras0.mp3", "files/bras1.mp3", "files/bras2.mp3", "files/bras3.mp3"]}, {"word": "brin", "number": 7, "filenames": ["files/brin0.mp3", "files/brin1.mp3", "files/brin2.mp3", "files/brin3.mp3", "files/brin4.mp3", "files/brin5.mp3", "files/brin6.mp3"]}, {"word": "brun", "number": 10, "filenames": ["files/brun0.mp3", "files/brun1.mp3", "files/brun2.mp3", "files/brun3.mp3", "files/brun4.mp3", "files/brun5.mp3", "files/brun6.mp3", "files/brun7.mp3", "files/brun8.mp3", "files/brun9.mp3"]}, {"word": "bus", "number": 4, "filenames": ["files/bus0.mp3", "files/bus1.mp3", "files/bus2.mp3", "files/bus3.mp3"]}, {"word": "but", "number": 4, "filenames": ["files/but0.mp3", "files/but1.mp3", "files/but2.mp3", "files/but3.mp3"]}, {"word": "by", "number": 1, "filenames": ["files/by0.mp3"]}, {"word": "b\u00e9ton", "number": 1, "filenames": ["files/b\u00e9ton0.mp3"]}, {"word": "c", "number": 3, "filenames": ["files/c0.mp3", "files/c1.mp3", "files/c2.mp3"]}, {"word": "cacher", "number": 1, "filenames": ["files/cacher0.mp3"]}, {"word": "cachet", "number": 1, "filenames": ["files/cachet0.mp3"]}, {"word": "camp", "number": 4, "filenames": ["files/camp0.mp3", "files/camp1.mp3", "files/camp2.mp3", "files/camp3.mp3"]}, {"word": "campo", "number": 1, "filenames": ["files/campo0.mp3"]}, {"word": "cap", "number": 1, "filenames": ["files/cap0.mp3"]}, {"word": "capot", "number": 2, "filenames": ["files/capot0.mp3", "files/capot1.mp3"]}, {"word": "car", "number": 5, "filenames": ["files/car0.mp3", "files/car1.mp3", "files/car2.mp3", "files/car3.mp3", "files/car4.mp3"]}, {"word": "carr\u00e9", "number": 5, "filenames": ["files/carr\u00e90.mp3", "files/carr\u00e91.mp3", "files/carr\u00e92.mp3", "files/carr\u00e93.mp3", "files/carr\u00e94.mp3"]}, {"word": "ce", "number": 3, "filenames": ["files/ce0.mp3", "files/ce1.mp3", "files/ce2.mp3"]}, {"word": "ceci", "number": 3, "filenames": ["files/ceci0.mp3", "files/ceci1.mp3", "files/ceci2.mp3"]}, {"word": "cens\u00e9", "number": 1, "filenames": ["files/cens\u00e90.mp3"]}, {"word": "cent", "number": 3, "filenames": ["files/cent0.mp3", "files/cent1.mp3", "files/cent2.mp3"]}, {"word": "cesse", "number": 1, "filenames": ["files/cesse0.mp3"]}, {"word": "cesser", "number": 1, "filenames": ["files/cesser0.mp3"]}, {"word": "ceux", "number": 4, "filenames": ["files/ceux0.mp3", "files/ceux1.mp3", "files/ceux2.mp3", "files/ceux3.mp3"]}, {"word": "champ", "number": 1, "filenames": ["files/champ0.mp3"]}, {"word": "chaque", "number": 3, "filenames": ["files/chaque0.mp3", "files/chaque1.mp3", "files/chaque2.mp3"]}, {"word": "chat", "number": 8, "filenames": ["files/chat0.mp3", "files/chat1.mp3", "files/chat2.mp3", "files/chat3.mp3", "files/chat4.mp3", "files/chat5.mp3", "files/chat6.mp3", "files/chat7.mp3"]}, {"word": "chaud", "number": 3, "filenames": ["files/chaud0.mp3", "files/chaud1.mp3", "files/chaud2.mp3"]}, {"word": "chevaux", "number": 5, "filenames": ["files/chevaux0.mp3", "files/chevaux1.mp3", "files/chevaux2.mp3", "files/chevaux3.mp3", "files/chevaux4.mp3"]}, {"word": "cheveux", "number": 5, "filenames": ["files/cheveux0.mp3", "files/cheveux1.mp3", "files/cheveux2.mp3", "files/cheveux3.mp3", "files/cheveux4.mp3"]}, {"word": "chez", "number": 5, "filenames": ["files/chez0.mp3", "files/chez1.mp3", "files/chez2.mp3", "files/chez3.mp3", "files/chez4.mp3"]}, {"word": "chic", "number": 2, "filenames": ["files/chic0.mp3", "files/chic1.mp3"]}, {"word": "choc", "number": 2, "filenames": ["files/choc0.mp3", "files/choc1.mp3"]}, {"word": "cinq", "number": 5, "filenames": ["files/cinq0.mp3", "files/cinq1.mp3", "files/cinq2.mp3", "files/cinq3.mp3", "files/cinq4.mp3"]}, {"word": "clan", "number": 2, "filenames": ["files/clan0.mp3", "files/clan1.mp3"]}, {"word": "clos", "number": 3, "filenames": ["files/clos0.mp3", "files/clos1.mp3", "files/clos2.mp3"]}, {"word": "cl\u00e9", "number": 2, "filenames": ["files/cl\u00e90.mp3", "files/cl\u00e91.mp3"]}, {"word": "coin", "number": 3, "filenames": ["files/coin0.mp3", "files/coin1.mp3", "files/coin2.mp3"]}, {"word": "colin", "number": 3, "filenames": ["files/colin0.mp3", "files/colin1.mp3", "files/colin2.mp3"]}, {"word": "colis", "number": 2, "filenames": ["files/colis0.mp3", "files/colis1.mp3"]}, {"word": "colle", "number": 1, "filenames": ["files/colle0.mp3"]}, {"word": "comment", "number": 7, "filenames": ["files/comment0.mp3", "files/comment1.mp3", "files/comment2.mp3", "files/comment3.mp3", "files/comment4.mp3", "files/comment5.mp3", "files/comment6.mp3"]}, {"word": "commis", "number": 3, "filenames": ["files/commis0.mp3", "files/commis1.mp3", "files/commis2.mp3"]}, {"word": "commun", "number": 2, "filenames": ["files/commun0.mp3", "files/commun1.mp3"]}, {"word": "comptait", "number": 1, "filenames": ["files/comptait0.mp3"]}, {"word": "compter", "number": 3, "filenames": ["files/compter0.mp3", "files/compter1.mp3", "files/compter2.mp3"]}, {"word": "conte", "number": 1, "filenames": ["files/conte0.mp3"]}, {"word": "conteneurs", "number": 1, "filenames": ["files/conteneurs0.mp3"]}, {"word": "contenir", "number": 1, "filenames": ["files/contenir0.mp3"]}, {"word": "cor\u00e9e", "number": 1, "filenames": ["files/cor\u00e9e0.mp3"]}, {"word": "cotait", "number": 1, "filenames": ["files/cotait0.mp3"]}, {"word": "cote", "number": 2, "filenames": ["files/cote0.mp3", "files/cote1.mp3"]}, {"word": "cot\u00e9", "number": 1, "filenames": ["files/cot\u00e90.mp3"]}, {"word": "coup", "number": 3, "filenames": ["files/coup0.mp3", "files/coup1.mp3", "files/coup2.mp3"]}, {"word": "coupe", "number": 4, "filenames": ["files/coupe0.mp3", "files/coupe1.mp3", "files/coupe2.mp3", "files/coupe3.mp3"]}, {"word": "coureurs", "number": 1, "filenames": ["files/coureurs0.mp3"]}, {"word": "courir", "number": 2, "filenames": ["files/courir0.mp3", "files/courir1.mp3"]}, {"word": "court", "number": 3, "filenames": ["files/court0.mp3", "files/court1.mp3", "files/court2.mp3"]}, {"word": "craint", "number": 2, "filenames": ["files/craint0.mp3", "files/craint1.mp3"]}, {"word": "cran", "number": 1, "filenames": ["files/cran0.mp3"]}, {"word": "creux", "number": 2, "filenames": ["files/creux0.mp3", "files/creux1.mp3"]}, {"word": "cri", "number": 1, "filenames": ["files/cri0.mp3"]}, {"word": "cru", "number": 3, "filenames": ["files/cru0.mp3", "files/cru1.mp3", "files/cru2.mp3"]}, {"word": "cr\u00e9e", "number": 2, "filenames": ["files/cr\u00e9e0.mp3", "files/cr\u00e9e1.mp3"]}, {"word": "cuit", "number": 3, "filenames": ["files/cuit0.mp3", "files/cuit1.mp3", "files/cuit2.mp3"]}, {"word": "cure", "number": 1, "filenames": ["files/cure0.mp3"]}, {"word": "c\u0153ur", "number": 4, "filenames": ["files/c\u0153ur0.mp3", "files/c\u0153ur1.mp3", "files/c\u0153ur2.mp3", "files/c\u0153ur3.mp3"]}, {"word": "d", "number": 3, "filenames": ["files/d0.mp3", "files/d1.mp3", "files/d2.mp3"]}, {"word": "danse", "number": 2, "filenames": ["files/danse0.mp3", "files/danse1.mp3"]}, {"word": "date", "number": 4, "filenames": ["files/date0.mp3", "files/date1.mp3", "files/date2.mp3", "files/date3.mp3"]}, {"word": "de", "number": 4, "filenames": ["files/de0.mp3", "files/de1.mp3", "files/de2.mp3", "files/de3.mp3"]}, {"word": "dent", "number": 4, "filenames": ["files/dent0.mp3", "files/dent1.mp3", "files/dent2.mp3", "files/dent3.mp3"]}, {"word": "der", "number": 0, "filenames": []}, {"word": "dette", "number": 2, "filenames": ["files/dette0.mp3", "files/dette1.mp3"]}, {"word": "deux", "number": 6, "filenames": ["files/deux0.mp3", "files/deux1.mp3", "files/deux2.mp3", "files/deux3.mp3", "files/deux4.mp3", "files/deux5.mp3"]}]